apppy/auth/__init__.py
apppy/auth/fixtures.py
apppy/auth/jwks.py
apppy/auth/jwks_test.py
apppy/auth/jwks_unit_test.py
apppy/auth/jwt.py
apppy/auth/jwt_unit_test.py
apppy/auth/oauth.py
apppy/auth/permissions.py
apppy/auth/errors/__init__.py
apppy/auth/errors/jwks.py
apppy/auth/errors/oauth.py
apppy/auth/errors/service.py
apppy/auth/errors/user.py
apppy/auth/test_examples/test.key.pem
apppy/auth/test_examples/test.pub.pem
apppy/auth/test_examples/unauthorized.key.pem
apppy_auth-0.23.2.dist-info/METADATA
apppy_auth-0.23.2.dist-info/WHEEL
apppy_auth-0.23.2.dist-info/RECORD
